README
setup.py
unipy_db/__init__.py
unipy_db/_version.py
unipy_db.egg-info/PKG-INFO
unipy_db.egg-info/SOURCES.txt
unipy_db.egg-info/dependency_links.txt
unipy_db.egg-info/not-zip-safe
unipy_db.egg-info/requires.txt
unipy_db.egg-info/top_level.txt
unipy_db/core/__init__.py
unipy_db/core/api.py
unipy_db/database/__init__.py
unipy_db/database/insert_query.py
unipy_db/database/select_query.py
unipy_db/database/select_query_oracle.py
unipy_db/test/__init__.py
unipy_db/test/async_db_test.py
unipy_db/util/__init__.py
unipy_db/util/api.py
unipy_db/util/wrapper.py