Metadata-Version: 1.1
Name: unipy-db
Version: 0.0.9
Summary: Useful tools for Data Scientists
Home-page: http://github.com/pydemia/unipy-db
Author: Young Ju Kim
Author-email: pydemia@gmail.com
License: MIT License
Platform: UNKNOWN
Classifier: Development Status :: 4 - Beta
Classifier: Environment :: Console
Classifier: Programming Language :: Python :: 3.5
Classifier: Operating System :: OS Independent
Classifier: Intended Audience :: End Users/Desktop
Classifier: Intended Audience :: Developers
Classifier: Intended Audience :: Science/Research
Classifier: Natural Language :: English
